{"vbc":216746,"rs":[{"cc":5587,"bo":46438,"v":15,"tot":8407,"per":"0.17","ser":"6405"},{"cc":5587,"bo":46439,"v":16,"tot":8407,"per":"0.19","ser":"6405"},{"cc":5587,"bo":46440,"v":451,"tot":8407,"per":"5.36","ser":"6405"},{"cc":5587,"bo":46441,"v":16,"tot":8407,"per":"0.19","ser":"6405"},{"cc":5587,"bo":46442,"v":39,"tot":8407,"per":"0.46","ser":"6405"},{"cc":5587,"bo":46443,"v":2,"tot":8407,"per":"0.02","ser":"6405"},{"cc":5587,"bo":46444,"v":5866,"tot":8407,"per":"69.77","ser":"6405"},{"cc":5587,"bo":46445,"v":6,"tot":8407,"per":"0.07","ser":"6405"},{"cc":5587,"bo":46446,"v":810,"tot":8407,"per":"9.63","ser":"6405"},{"cc":5587,"bo":46447,"v":1186,"tot":8407,"per":"14.10","ser":"6405"},{"cc":5588,"bo":46448,"v":32,"tot":8066,"per":"0.39","ser":"6405"},{"cc":5588,"bo":46449,"v":29,"tot":8066,"per":"0.35","ser":"6405"},{"cc":5588,"bo":46450,"v":3,"tot":8066,"per":"0.03","ser":"6405"},{"cc":5588,"bo":46451,"v":7002,"tot":8066,"per":"86.80","ser":"6405"},{"cc":5588,"bo":46452,"v":14,"tot":8066,"per":"0.17","ser":"6405"},{"cc":5588,"bo":46453,"v":149,"tot":8066,"per":"1.84","ser":"6405"},{"cc":5588,"bo":46454,"v":546,"tot":8066,"per":"6.76","ser":"6405"},{"cc":5588,"bo":46455,"v":10,"tot":8066,"per":"0.12","ser":"6405"},{"cc":5588,"bo":46456,"v":281,"tot":8066,"per":"3.48","ser":"6405"},{"cc":5589,"bo":46457,"v":99,"tot":53018,"per":"0.18","ser":"6405"},{"cc":5589,"bo":46458,"v":78,"tot":53018,"per":"0.14","ser":"6405"},{"cc":5589,"bo":46459,"v":73,"tot":53018,"per":"0.13","ser":"6405"},{"cc":5589,"bo":46460,"v":230,"tot":53018,"per":"0.43","ser":"6405"},{"cc":5589,"bo":46461,"v":63,"tot":53018,"per":"0.11","ser":"6405"},{"cc":5589,"bo":46462,"v":474,"tot":53018,"per":"0.89","ser":"6405"},{"cc":5589,"bo":46463,"v":144,"tot":53018,"per":"0.27","ser":"6405"},{"cc":5589,"bo":46464,"v":1785,"tot":53018,"per":"3.36","ser":"6405"},{"cc":5589,"bo":46465,"v":402,"tot":53018,"per":"0.75","ser":"6405"},{"cc":5589,"bo":46466,"v":498,"tot":53018,"per":"0.93","ser":"6405"},{"cc":5589,"bo":46467,"v":1559,"tot":53018,"per":"2.94","ser":"6405"},{"cc":5589,"bo":46468,"v":66,"tot":53018,"per":"0.12","ser":"6405"},{"cc":5589,"bo":46469,"v":120,"tot":53018,"per":"0.22","ser":"6405"},{"cc":5589,"bo":46470,"v":2543,"tot":53018,"per":"4.79","ser":"6405"},{"cc":5589,"bo":46471,"v":132,"tot":53018,"per":"0.24","ser":"6405"},{"cc":5589,"bo":46472,"v":395,"tot":53018,"per":"0.74","ser":"6405"},{"cc":5589,"bo":46473,"v":72,"tot":53018,"per":"0.13","ser":"6405"},{"cc":5589,"bo":46474,"v":441,"tot":53018,"per":"0.83","ser":"6405"},{"cc":5589,"bo":46475,"v":433,"tot":53018,"per":"0.81","ser":"6405"},{"cc":5589,"bo":46476,"v":74,"tot":53018,"per":"0.13","ser":"6405"},{"cc":5589,"bo":46477,"v":757,"tot":53018,"per":"1.42","ser":"6405"},{"cc":5589,"bo":46478,"v":1659,"tot":53018,"per":"3.12","ser":"6405"},{"cc":5589,"bo":46479,"v":882,"tot":53018,"per":"1.66","ser":"6405"},{"cc":5589,"bo":46480,"v":69,"tot":53018,"per":"0.13","ser":"6405"},{"cc":5589,"bo":46481,"v":2167,"tot":53018,"per":"4.08","ser":"6405"},{"cc":5589,"bo":46482,"v":221,"tot":53018,"per":"0.41","ser":"6405"},{"cc":5589,"bo":46483,"v":1819,"tot":53018,"per":"3.43","ser":"6405"},{"cc":5589,"bo":46484,"v":53,"tot":53018,"per":"0.09","ser":"6405"},{"cc":5589,"bo":46485,"v":1387,"tot":53018,"per":"2.61","ser":"6405"},{"cc":5589,"bo":46486,"v":2065,"tot":53018,"per":"3.89","ser":"6405"},{"cc":5589,"bo":46487,"v":785,"tot":53018,"per":"1.48","ser":"6405"},{"cc":5589,"bo":46488,"v":123,"tot":53018,"per":"0.23","ser":"6405"},{"cc":5589,"bo":46489,"v":1151,"tot":53018,"per":"2.17","ser":"6405"},{"cc":5589,"bo":46490,"v":1811,"tot":53018,"per":"3.41","ser":"6405"},{"cc":5589,"bo":46491,"v":46,"tot":53018,"per":"0.08","ser":"6405"},{"cc":5589,"bo":46492,"v":42,"tot":53018,"per":"0.07","ser":"6405"},{"cc":5589,"bo":46493,"v":86,"tot":53018,"per":"0.16","ser":"6405"},{"cc":5589,"bo":46494,"v":413,"tot":53018,"per":"0.77","ser":"6405"},{"cc":5589,"bo":46495,"v":160,"tot":53018,"per":"0.30","ser":"6405"},{"cc":5589,"bo":46496,"v":2927,"tot":53018,"per":"5.52","ser":"6405"},{"cc":5589,"bo":46497,"v":79,"tot":53018,"per":"0.14","ser":"6405"},{"cc":5589,"bo":46498,"v":52,"tot":53018,"per":"0.09","ser":"6405"},{"cc":5589,"bo":46499,"v":467,"tot":53018,"per":"0.88","ser":"6405"},{"cc":5589,"bo":46500,"v":517,"tot":53018,"per":"0.97","ser":"6405"},{"cc":5589,"bo":46501,"v":161,"tot":53018,"per":"0.30","ser":"6405"},{"cc":5589,"bo":46502,"v":38,"tot":53018,"per":"0.07","ser":"6405"},{"cc":5589,"bo":46503,"v":79,"tot":53018,"per":"0.14","ser":"6405"},{"cc":5589,"bo":46504,"v":582,"tot":53018,"per":"1.09","ser":"6405"},{"cc":5589,"bo":46505,"v":4564,"tot":53018,"per":"8.60","ser":"6405"},{"cc":5589,"bo":46506,"v":1094,"tot":53018,"per":"2.06","ser":"6405"},{"cc":5589,"bo":46507,"v":376,"tot":53018,"per":"0.70","ser":"6405"},{"cc":5589,"bo":46508,"v":500,"tot":53018,"per":"0.94","ser":"6405"},{"cc":5589,"bo":46509,"v":64,"tot":53018,"per":"0.12","ser":"6405"},{"cc":5589,"bo":46510,"v":2212,"tot":53018,"per":"4.17","ser":"6405"},{"cc":5589,"bo":46511,"v":55,"tot":53018,"per":"0.10","ser":"6405"},{"cc":5589,"bo":46512,"v":309,"tot":53018,"per":"0.58","ser":"6405"},{"cc":5589,"bo":46513,"v":2359,"tot":53018,"per":"4.44","ser":"6405"},{"cc":5589,"bo":46514,"v":513,"tot":53018,"per":"0.96","ser":"6405"},{"cc":5589,"bo":46515,"v":3251,"tot":53018,"per":"6.13","ser":"6405"},{"cc":5589,"bo":46516,"v":54,"tot":53018,"per":"0.10","ser":"6405"},{"cc":5589,"bo":46517,"v":2107,"tot":53018,"per":"3.97","ser":"6405"},{"cc":5589,"bo":46518,"v":2801,"tot":53018,"per":"5.28","ser":"6405"},{"cc":5589,"bo":46519,"v":114,"tot":53018,"per":"0.21","ser":"6405"},{"cc":5589,"bo":46520,"v":2366,"tot":53018,"per":"4.46","ser":"6405"},{"cc":5652,"bo":46731,"v":5274,"tot":5274,"per":"100.00","ser":"6405"},{"cc":5733,"bo":46956,"v":4872,"tot":4872,"per":"100.00","ser":"6405"},{"cc":5939,"bo":48513,"v":709,"tot":18243,"per":"3.88","ser":"6405"},{"cc":5939,"bo":48514,"v":518,"tot":18243,"per":"2.83","ser":"6405"},{"cc":5939,"bo":48515,"v":2149,"tot":18243,"per":"11.77","ser":"6405"},{"cc":5939,"bo":48516,"v":1836,"tot":18243,"per":"10.06","ser":"6405"},{"cc":5939,"bo":48517,"v":271,"tot":18243,"per":"1.48","ser":"6405"},{"cc":5939,"bo":48518,"v":1638,"tot":18243,"per":"8.97","ser":"6405"},{"cc":5939,"bo":48519,"v":4200,"tot":18243,"per":"23.02","ser":"6405"},{"cc":5939,"bo":48520,"v":3385,"tot":18243,"per":"18.55","ser":"6405"},{"cc":5939,"bo":48521,"v":3537,"tot":18243,"per":"19.38","ser":"6405"},{"cc":6171,"bo":49426,"v":82,"tot":7547,"per":"1.08","ser":"6405"},{"cc":6171,"bo":49427,"v":44,"tot":7547,"per":"0.58","ser":"6405"},{"cc":6171,"bo":49428,"v":72,"tot":7547,"per":"0.95","ser":"6405"},{"cc":6171,"bo":49429,"v":3109,"tot":7547,"per":"41.19","ser":"6405"},{"cc":6171,"bo":49430,"v":28,"tot":7547,"per":"0.37","ser":"6405"},{"cc":6171,"bo":49431,"v":4212,"tot":7547,"per":"55.81","ser":"6405"},{"cc":7591,"bo":53203,"v":3494,"tot":8272,"per":"42.23","ser":"6405"},{"cc":7591,"bo":53204,"v":4778,"tot":8272,"per":"57.76","ser":"6405"},{"cc":9225,"bo":57088,"v":1414,"tot":7249,"per":"19.50","ser":"6405"},{"cc":9225,"bo":57089,"v":5835,"tot":7249,"per":"80.49","ser":"6405"},{"cc":10876,"bo":86624,"v":1645,"tot":55934,"per":"2.94","ser":"6405"},{"cc":10876,"bo":86625,"v":3827,"tot":55934,"per":"6.84","ser":"6405"},{"cc":10876,"bo":86626,"v":5072,"tot":55934,"per":"9.06","ser":"6405"},{"cc":10876,"bo":86627,"v":2771,"tot":55934,"per":"4.95","ser":"6405"},{"cc":10876,"bo":86628,"v":3128,"tot":55934,"per":"5.59","ser":"6405"},{"cc":10876,"bo":86629,"v":1419,"tot":55934,"per":"2.53","ser":"6405"},{"cc":10876,"bo":86630,"v":4057,"tot":55934,"per":"7.25","ser":"6405"},{"cc":10876,"bo":86631,"v":2616,"tot":55934,"per":"4.67","ser":"6405"},{"cc":10876,"bo":86632,"v":1336,"tot":55934,"per":"2.38","ser":"6405"},{"cc":10876,"bo":86633,"v":3454,"tot":55934,"per":"6.17","ser":"6405"},{"cc":10876,"bo":86634,"v":4802,"tot":55934,"per":"8.58","ser":"6405"},{"cc":10876,"bo":86635,"v":3544,"tot":55934,"per":"6.33","ser":"6405"},{"cc":10876,"bo":86636,"v":3026,"tot":55934,"per":"5.40","ser":"6405"},{"cc":10876,"bo":86637,"v":4733,"tot":55934,"per":"8.46","ser":"6405"},{"cc":10876,"bo":86638,"v":3833,"tot":55934,"per":"6.85","ser":"6405"},{"cc":10876,"bo":86639,"v":3879,"tot":55934,"per":"6.93","ser":"6405"},{"cc":10876,"bo":86640,"v":2792,"tot":55934,"per":"4.99","ser":"6405"},{"cc":11172,"bo":92698,"v":4,"tot":5869,"per":"0.06","ser":"6405"},{"cc":11172,"bo":92699,"v":2,"tot":5869,"per":"0.03","ser":"6405"},{"cc":11172,"bo":92700,"v":2,"tot":5869,"per":"0.03","ser":"6405"},{"cc":11172,"bo":92701,"v":6,"tot":5869,"per":"0.10","ser":"6405"},{"cc":11172,"bo":92702,"v":19,"tot":5869,"per":"0.32","ser":"6405"},{"cc":11172,"bo":92703,"v":1,"tot":5869,"per":"0.01","ser":"6405"},{"cc":11172,"bo":92704,"v":2,"tot":5869,"per":"0.03","ser":"6405"},{"cc":11172,"bo":92705,"v":1,"tot":5869,"per":"0.01","ser":"6405"},{"cc":11172,"bo":92706,"v":4,"tot":5869,"per":"0.06","ser":"6405"},{"cc":11172,"bo":92707,"v":5,"tot":5869,"per":"0.08","ser":"6405"},{"cc":11172,"bo":92708,"v":20,"tot":5869,"per":"0.34","ser":"6405"},{"cc":11172,"bo":92709,"v":1,"tot":5869,"per":"0.01","ser":"6405"},{"cc":11172,"bo":92710,"v":1,"tot":5869,"per":"0.01","ser":"6405"},{"cc":11172,"bo":92711,"v":27,"tot":5869,"per":"0.46","ser":"6405"},{"cc":11172,"bo":92712,"v":11,"tot":5869,"per":"0.18","ser":"6405"},{"cc":11172,"bo":92713,"v":1,"tot":5869,"per":"0.01","ser":"6405"},{"cc":11172,"bo":92714,"v":1,"tot":5869,"per":"0.01","ser":"6405"},{"cc":11172,"bo":92715,"v":5,"tot":5869,"per":"0.08","ser":"6405"},{"cc":11172,"bo":92716,"v":7,"tot":5869,"per":"0.11","ser":"6405"},{"cc":11172,"bo":92717,"v":61,"tot":5869,"per":"1.03","ser":"6405"},{"cc":11172,"bo":92718,"v":3,"tot":5869,"per":"0.05","ser":"6405"},{"cc":11172,"bo":92719,"v":7,"tot":5869,"per":"0.11","ser":"6405"},{"cc":11172,"bo":92720,"v":1,"tot":5869,"per":"0.01","ser":"6405"},{"cc":11172,"bo":92721,"v":0,"tot":5869,"per":"0.00","ser":"6405"},{"cc":11172,"bo":92722,"v":10,"tot":5869,"per":"0.17","ser":"6405"},{"cc":11172,"bo":92723,"v":5,"tot":5869,"per":"0.08","ser":"6405"},{"cc":11172,"bo":92724,"v":4,"tot":5869,"per":"0.06","ser":"6405"},{"cc":11172,"bo":92725,"v":97,"tot":5869,"per":"1.65","ser":"6405"},{"cc":11172,"bo":92726,"v":2,"tot":5869,"per":"0.03","ser":"6405"},{"cc":11172,"bo":92727,"v":22,"tot":5869,"per":"0.37","ser":"6405"},{"cc":11172,"bo":92728,"v":39,"tot":5869,"per":"0.66","ser":"6405"},{"cc":11172,"bo":92729,"v":1,"tot":5869,"per":"0.01","ser":"6405"},{"cc":11172,"bo":92730,"v":1,"tot":5869,"per":"0.01","ser":"6405"},{"cc":11172,"bo":92731,"v":0,"tot":5869,"per":"0.00","ser":"6405"},{"cc":11172,"bo":92732,"v":30,"tot":5869,"per":"0.51","ser":"6405"},{"cc":11172,"bo":92733,"v":0,"tot":5869,"per":"0.00","ser":"6405"},{"cc":11172,"bo":92734,"v":1,"tot":5869,"per":"0.01","ser":"6405"},{"cc":11172,"bo":92735,"v":6,"tot":5869,"per":"0.10","ser":"6405"},{"cc":11172,"bo":92736,"v":42,"tot":5869,"per":"0.71","ser":"6405"},{"cc":11172,"bo":92737,"v":1,"tot":5869,"per":"0.01","ser":"6405"},{"cc":11172,"bo":92738,"v":2,"tot":5869,"per":"0.03","ser":"6405"},{"cc":11172,"bo":92739,"v":6,"tot":5869,"per":"0.10","ser":"6405"},{"cc":11172,"bo":92740,"v":32,"tot":5869,"per":"0.54","ser":"6405"},{"cc":11172,"bo":92741,"v":0,"tot":5869,"per":"0.00","ser":"6405"},{"cc":11172,"bo":92742,"v":4,"tot":5869,"per":"0.06","ser":"6405"},{"cc":11172,"bo":92743,"v":9,"tot":5869,"per":"0.15","ser":"6405"},{"cc":11172,"bo":92744,"v":1,"tot":5869,"per":"0.01","ser":"6405"},{"cc":11172,"bo":92745,"v":1,"tot":5869,"per":"0.01","ser":"6405"},{"cc":11172,"bo":92746,"v":13,"tot":5869,"per":"0.22","ser":"6405"},{"cc":11172,"bo":92747,"v":18,"tot":5869,"per":"0.30","ser":"6405"},{"cc":11172,"bo":92748,"v":2,"tot":5869,"per":"0.03","ser":"6405"},{"cc":11172,"bo":92749,"v":1,"tot":5869,"per":"0.01","ser":"6405"},{"cc":11172,"bo":92750,"v":5,"tot":5869,"per":"0.08","ser":"6405"},{"cc":11172,"bo":92751,"v":8,"tot":5869,"per":"0.13","ser":"6405"},{"cc":11172,"bo":92752,"v":377,"tot":5869,"per":"6.42","ser":"6405"},{"cc":11172,"bo":92753,"v":2,"tot":5869,"per":"0.03","ser":"6405"},{"cc":11172,"bo":92754,"v":1,"tot":5869,"per":"0.01","ser":"6405"},{"cc":11172,"bo":92755,"v":1,"tot":5869,"per":"0.01","ser":"6405"},{"cc":11172,"bo":92756,"v":2,"tot":5869,"per":"0.03","ser":"6405"},{"cc":11172,"bo":92757,"v":4,"tot":5869,"per":"0.06","ser":"6405"},{"cc":11172,"bo":92758,"v":21,"tot":5869,"per":"0.35","ser":"6405"},{"cc":11172,"bo":92759,"v":2,"tot":5869,"per":"0.03","ser":"6405"},{"cc":11172,"bo":92760,"v":1,"tot":5869,"per":"0.01","ser":"6405"},{"cc":11172,"bo":92761,"v":0,"tot":5869,"per":"0.00","ser":"6405"},{"cc":11172,"bo":92762,"v":1,"tot":5869,"per":"0.01","ser":"6405"},{"cc":11172,"bo":92763,"v":0,"tot":5869,"per":"0.00","ser":"6405"},{"cc":11172,"bo":92764,"v":6,"tot":5869,"per":"0.10","ser":"6405"},{"cc":11172,"bo":92765,"v":43,"tot":5869,"per":"0.73","ser":"6405"},{"cc":11172,"bo":92766,"v":2,"tot":5869,"per":"0.03","ser":"6405"},{"cc":11172,"bo":92767,"v":0,"tot":5869,"per":"0.00","ser":"6405"},{"cc":11172,"bo":92768,"v":1,"tot":5869,"per":"0.01","ser":"6405"},{"cc":11172,"bo":92769,"v":35,"tot":5869,"per":"0.59","ser":"6405"},{"cc":11172,"bo":92770,"v":2,"tot":5869,"per":"0.03","ser":"6405"},{"cc":11172,"bo":92771,"v":4,"tot":5869,"per":"0.06","ser":"6405"},{"cc":11172,"bo":92772,"v":0,"tot":5869,"per":"0.00","ser":"6405"},{"cc":11172,"bo":92773,"v":5,"tot":5869,"per":"0.08","ser":"6405"},{"cc":11172,"bo":92774,"v":1,"tot":5869,"per":"0.01","ser":"6405"},{"cc":11172,"bo":92775,"v":7,"tot":5869,"per":"0.11","ser":"6405"},{"cc":11172,"bo":92776,"v":0,"tot":5869,"per":"0.00","ser":"6405"},{"cc":11172,"bo":92777,"v":2,"tot":5869,"per":"0.03","ser":"6405"},{"cc":11172,"bo":92778,"v":74,"tot":5869,"per":"1.26","ser":"6405"},{"cc":11172,"bo":92779,"v":0,"tot":5869,"per":"0.00","ser":"6405"},{"cc":11172,"bo":92780,"v":0,"tot":5869,"per":"0.00","ser":"6405"},{"cc":11172,"bo":92781,"v":0,"tot":5869,"per":"0.00","ser":"6405"},{"cc":11172,"bo":92782,"v":3,"tot":5869,"per":"0.05","ser":"6405"},{"cc":11172,"bo":92783,"v":1328,"tot":5869,"per":"22.62","ser":"6405"},{"cc":11172,"bo":92784,"v":4,"tot":5869,"per":"0.06","ser":"6405"},{"cc":11172,"bo":92785,"v":4,"tot":5869,"per":"0.06","ser":"6405"},{"cc":11172,"bo":92786,"v":1,"tot":5869,"per":"0.01","ser":"6405"},{"cc":11172,"bo":92787,"v":12,"tot":5869,"per":"0.20","ser":"6405"},{"cc":11172,"bo":92788,"v":5,"tot":5869,"per":"0.08","ser":"6405"},{"cc":11172,"bo":92789,"v":9,"tot":5869,"per":"0.15","ser":"6405"},{"cc":11172,"bo":92790,"v":50,"tot":5869,"per":"0.85","ser":"6405"},{"cc":11172,"bo":92791,"v":4,"tot":5869,"per":"0.06","ser":"6405"},{"cc":11172,"bo":92792,"v":13,"tot":5869,"per":"0.22","ser":"6405"},{"cc":11172,"bo":92793,"v":3,"tot":5869,"per":"0.05","ser":"6405"},{"cc":11172,"bo":92794,"v":1,"tot":5869,"per":"0.01","ser":"6405"},{"cc":11172,"bo":92795,"v":1,"tot":5869,"per":"0.01","ser":"6405"},{"cc":11172,"bo":92796,"v":6,"tot":5869,"per":"0.10","ser":"6405"},{"cc":11172,"bo":92797,"v":9,"tot":5869,"per":"0.15","ser":"6405"},{"cc":11172,"bo":92798,"v":1,"tot":5869,"per":"0.01","ser":"6405"},{"cc":11172,"bo":92799,"v":1,"tot":5869,"per":"0.01","ser":"6405"},{"cc":11172,"bo":92800,"v":0,"tot":5869,"per":"0.00","ser":"6405"},{"cc":11172,"bo":92801,"v":9,"tot":5869,"per":"0.15","ser":"6405"},{"cc":11172,"bo":92802,"v":0,"tot":5869,"per":"0.00","ser":"6405"},{"cc":11172,"bo":92803,"v":1,"tot":5869,"per":"0.01","ser":"6405"},{"cc":11172,"bo":92804,"v":4,"tot":5869,"per":"0.06","ser":"6405"},{"cc":11172,"bo":92805,"v":10,"tot":5869,"per":"0.17","ser":"6405"},{"cc":11172,"bo":92806,"v":817,"tot":5869,"per":"13.92","ser":"6405"},{"cc":11172,"bo":92807,"v":7,"tot":5869,"per":"0.11","ser":"6405"},{"cc":11172,"bo":92808,"v":1,"tot":5869,"per":"0.01","ser":"6405"},{"cc":11172,"bo":92809,"v":2,"tot":5869,"per":"0.03","ser":"6405"},{"cc":11172,"bo":92810,"v":0,"tot":5869,"per":"0.00","ser":"6405"},{"cc":11172,"bo":92811,"v":9,"tot":5869,"per":"0.15","ser":"6405"},{"cc":11172,"bo":92812,"v":6,"tot":5869,"per":"0.10","ser":"6405"},{"cc":11172,"bo":92813,"v":38,"tot":5869,"per":"0.64","ser":"6405"},{"cc":11172,"bo":92814,"v":2,"tot":5869,"per":"0.03","ser":"6405"},{"cc":11172,"bo":92815,"v":0,"tot":5869,"per":"0.00","ser":"6405"},{"cc":11172,"bo":92816,"v":3,"tot":5869,"per":"0.05","ser":"6405"},{"cc":11172,"bo":92817,"v":0,"tot":5869,"per":"0.00","ser":"6405"},{"cc":11172,"bo":92818,"v":0,"tot":5869,"per":"0.00","ser":"6405"},{"cc":11172,"bo":92819,"v":0,"tot":5869,"per":"0.00","ser":"6405"},{"cc":11172,"bo":92820,"v":8,"tot":5869,"per":"0.13","ser":"6405"},{"cc":11172,"bo":92821,"v":1223,"tot":5869,"per":"20.83","ser":"6405"},{"cc":11172,"bo":92822,"v":3,"tot":5869,"per":"0.05","ser":"6405"},{"cc":11172,"bo":92823,"v":4,"tot":5869,"per":"0.06","ser":"6405"},{"cc":11172,"bo":92824,"v":10,"tot":5869,"per":"0.17","ser":"6405"},{"cc":11172,"bo":92825,"v":5,"tot":5869,"per":"0.08","ser":"6405"},{"cc":11172,"bo":92826,"v":3,"tot":5869,"per":"0.05","ser":"6405"},{"cc":11172,"bo":92827,"v":0,"tot":5869,"per":"0.00","ser":"6405"},{"cc":11172,"bo":92828,"v":3,"tot":5869,"per":"0.05","ser":"6405"},{"cc":11172,"bo":92829,"v":1,"tot":5869,"per":"0.01","ser":"6405"},{"cc":11172,"bo":92830,"v":0,"tot":5869,"per":"0.00","ser":"6405"},{"cc":11172,"bo":92831,"v":1,"tot":5869,"per":"0.01","ser":"6405"},{"cc":11172,"bo":92832,"v":43,"tot":5869,"per":"0.73","ser":"6405"},{"cc":11172,"bo":92833,"v":54,"tot":5869,"per":"0.92","ser":"6405"},{"cc":11172,"bo":92834,"v":2,"tot":5869,"per":"0.03","ser":"6405"},{"cc":11172,"bo":92835,"v":1,"tot":5869,"per":"0.01","ser":"6405"},{"cc":11172,"bo":92836,"v":20,"tot":5869,"per":"0.34","ser":"6405"},{"cc":11172,"bo":92837,"v":3,"tot":5869,"per":"0.05","ser":"6405"},{"cc":11172,"bo":92838,"v":4,"tot":5869,"per":"0.06","ser":"6405"},{"cc":11172,"bo":92839,"v":1,"tot":5869,"per":"0.01","ser":"6405"},{"cc":11172,"bo":92840,"v":2,"tot":5869,"per":"0.03","ser":"6405"},{"cc":11172,"bo":92841,"v":1,"tot":5869,"per":"0.01","ser":"6405"},{"cc":11172,"bo":92842,"v":52,"tot":5869,"per":"0.88","ser":"6405"},{"cc":11172,"bo":92843,"v":2,"tot":5869,"per":"0.03","ser":"6405"},{"cc":11172,"bo":92844,"v":4,"tot":5869,"per":"0.06","ser":"6405"},{"cc":11172,"bo":92845,"v":8,"tot":5869,"per":"0.13","ser":"6405"},{"cc":11172,"bo":92846,"v":6,"tot":5869,"per":"0.10","ser":"6405"},{"cc":11172,"bo":92847,"v":0,"tot":5869,"per":"0.00","ser":"6405"},{"cc":11172,"bo":92848,"v":26,"tot":5869,"per":"0.44","ser":"6405"},{"cc":11172,"bo":92849,"v":1,"tot":5869,"per":"0.01","ser":"6405"},{"cc":11172,"bo":92850,"v":1,"tot":5869,"per":"0.01","ser":"6405"},{"cc":11172,"bo":92851,"v":0,"tot":5869,"per":"0.00","ser":"6405"},{"cc":11172,"bo":92852,"v":0,"tot":5869,"per":"0.00","ser":"6405"},{"cc":11172,"bo":92853,"v":123,"tot":5869,"per":"2.09","ser":"6405"},{"cc":11172,"bo":92854,"v":69,"tot":5869,"per":"1.17","ser":"6405"},{"cc":11172,"bo":92855,"v":1,"tot":5869,"per":"0.01","ser":"6405"},{"cc":11172,"bo":92856,"v":0,"tot":5869,"per":"0.00","ser":"6405"},{"cc":11172,"bo":92857,"v":13,"tot":5869,"per":"0.22","ser":"6405"},{"cc":11172,"bo":92858,"v":5,"tot":5869,"per":"0.08","ser":"6405"},{"cc":11172,"bo":92859,"v":545,"tot":5869,"per":"9.28","ser":"6405"},{"cc":11172,"bo":92860,"v":38,"tot":5869,"per":"0.64","ser":"6405"},{"cc":11172,"bo":92861,"v":1,"tot":5869,"per":"0.01","ser":"6405"},{"cc":11172,"bo":92862,"v":1,"tot":5869,"per":"0.01","ser":"6405"},{"cc":11172,"bo":92863,"v":0,"tot":5869,"per":"0.00","ser":"6405"},{"cc":11172,"bo":92864,"v":0,"tot":5869,"per":"0.00","ser":"6405"},{"cc":11172,"bo":92865,"v":47,"tot":5869,"per":"0.80","ser":"6405"},{"cc":11172,"bo":92866,"v":0,"tot":5869,"per":"0.00","ser":"6405"},{"cc":11172,"bo":92867,"v":1,"tot":5869,"per":"0.01","ser":"6405"},{"cc":11172,"bo":92868,"v":0,"tot":5869,"per":"0.00","ser":"6405"},{"cc":11172,"bo":92869,"v":0,"tot":5869,"per":"0.00","ser":"6405"},{"cc":11172,"bo":92870,"v":3,"tot":5869,"per":"0.05","ser":"6405"},{"cc":11172,"bo":92871,"v":5,"tot":5869,"per":"0.08","ser":"6405"},{"cc":11172,"bo":92872,"v":3,"tot":5869,"per":"0.05","ser":"6405"},{"cc":11172,"bo":92873,"v":9,"tot":5869,"per":"0.15","ser":"6405"},{"cc":11172,"bo":92874,"v":0,"tot":5869,"per":"0.00","ser":"6405"}],"cos":[{"cc":5587,"cn":"blank","ct":499},{"cc":5587,"cn":"blank-ballots","ct":122},{"cc":5587,"cn":"contest-abstention-votes","ct":122},{"cc":5587,"cn":"expected-vb","ct":22},{"cc":5587,"cn":"expected-voters","ct":10711},{"cc":5587,"cn":"fake-ballots","ct":36},{"cc":5587,"cn":"fill-up-rate","ct":93},{"cc":5587,"cn":"misfeed-ballots","ct":562},{"cc":5587,"cn":"number-of-voters-who-actually-voted","ct":9077},{"cc":5587,"cn":"overvote-ballots","ct":888},{"cc":5587,"cn":"overvote-count","ct":171},{"cc":5587,"cn":"overvotes","ct":305},{"cc":5587,"cn":"processed-ballots","ct":9077},{"cc":5587,"cn":"processed-count","ct":9077},{"cc":5587,"cn":"reported-expected-precincts","ct":22},{"cc":5587,"cn":"reported-expected-voters","ct":10711},{"cc":5587,"cn":"reported-precincts","ct":22},{"cc":5587,"cn":"reported-vb","ct":22},{"cc":5587,"cn":"reported-voters","ct":10711},{"cc":5587,"cn":"returned-ballots","ct":613},{"cc":5587,"cn":"rezeros","ct":44},{"cc":5587,"cn":"tra-vb","ct":100},{"cc":5587,"cn":"turn-out","ct":84.74},{"cc":5587,"cn":"under-votes","ct":377},{"cc":5587,"cn":"undervote-ballots","ct":8018},{"cc":5587,"cn":"undervote-count","ct":499},{"cc":5587,"cn":"undervotes","ct":499},{"cc":5587,"cn":"valid-ballot-rate","ct":100},{"cc":5587,"cn":"valid-votes","ct":9077},{"cc":5587,"cn":"votes-obtained-by-all-candidates","ct":8407},{"cc":5587,"cn":"writein-ballots","ct":0},{"cc":5588,"cn":"blank","ct":896},{"cc":5588,"cn":"blank-ballots","ct":122},{"cc":5588,"cn":"contest-abstention-votes","ct":122},{"cc":5588,"cn":"expected-vb","ct":22},{"cc":5588,"cn":"expected-voters","ct":10711},{"cc":5588,"cn":"fake-ballots","ct":36},{"cc":5588,"cn":"fill-up-rate","ct":89},{"cc":5588,"cn":"misfeed-ballots","ct":562},{"cc":5588,"cn":"number-of-voters-who-actually-voted","ct":9077},{"cc":5588,"cn":"overvote-ballots","ct":888},{"cc":5588,"cn":"overvote-count","ct":115},{"cc":5588,"cn":"overvotes","ct":191},{"cc":5588,"cn":"processed-ballots","ct":9077},{"cc":5588,"cn":"processed-count","ct":9077},{"cc":5588,"cn":"reported-expected-precincts","ct":22},{"cc":5588,"cn":"reported-expected-voters","ct":10711},{"cc":5588,"cn":"reported-precincts","ct":22},{"cc":5588,"cn":"reported-vb","ct":22},{"cc":5588,"cn":"reported-voters","ct":10711},{"cc":5588,"cn":"returned-ballots","ct":613},{"cc":5588,"cn":"rezeros","ct":44},{"cc":5588,"cn":"tra-vb","ct":100},{"cc":5588,"cn":"turn-out","ct":84.74},{"cc":5588,"cn":"under-votes","ct":774},{"cc":5588,"cn":"undervote-ballots","ct":8018},{"cc":5588,"cn":"undervote-count","ct":896},{"cc":5588,"cn":"undervotes","ct":896},{"cc":5588,"cn":"valid-ballot-rate","ct":100},{"cc":5588,"cn":"valid-votes","ct":9077},{"cc":5588,"cn":"votes-obtained-by-all-candidates","ct":8066},{"cc":5588,"cn":"writein-ballots","ct":0},{"cc":5589,"cn":"blank","ct":1519},{"cc":5589,"cn":"blank-ballots","ct":122},{"cc":5589,"cn":"contest-abstention-votes","ct":1464},{"cc":5589,"cn":"expected-vb","ct":22},{"cc":5589,"cn":"expected-voters","ct":10711},{"cc":5589,"cn":"fake-ballots","ct":36},{"cc":5589,"cn":"fill-up-rate","ct":49},{"cc":5589,"cn":"misfeed-ballots","ct":562},{"cc":5589,"cn":"number-of-voters-who-actually-voted","ct":9077},{"cc":5589,"cn":"overvote-ballots","ct":888},{"cc":5589,"cn":"overvote-count","ct":82},{"cc":5589,"cn":"overvotes","ct":275},{"cc":5589,"cn":"processed-ballots","ct":9077},{"cc":5589,"cn":"processed-count","ct":9077},{"cc":5589,"cn":"reported-expected-precincts","ct":22},{"cc":5589,"cn":"reported-expected-voters","ct":10711},{"cc":5589,"cn":"reported-precincts","ct":22},{"cc":5589,"cn":"reported-vb","ct":22},{"cc":5589,"cn":"reported-voters","ct":10711},{"cc":5589,"cn":"returned-ballots","ct":613},{"cc":5589,"cn":"rezeros","ct":44},{"cc":5589,"cn":"tra-vb","ct":100},{"cc":5589,"cn":"turn-out","ct":84.74},{"cc":5589,"cn":"under-votes","ct":53458},{"cc":5589,"cn":"undervote-ballots","ct":8018},{"cc":5589,"cn":"undervote-count","ct":6778},{"cc":5589,"cn":"undervotes","ct":54922},{"cc":5589,"cn":"valid-ballot-rate","ct":100},{"cc":5589,"cn":"valid-votes","ct":108924},{"cc":5589,"cn":"votes-obtained-by-all-candidates","ct":53018},{"cc":5589,"cn":"writein-ballots","ct":0},{"cc":5652,"cn":"blank","ct":3803},{"cc":5652,"cn":"blank-ballots","ct":122},{"cc":5652,"cn":"contest-abstention-votes","ct":122},{"cc":5652,"cn":"expected-vb","ct":22},{"cc":5652,"cn":"expected-voters","ct":10711},{"cc":5652,"cn":"fake-ballots","ct":36},{"cc":5652,"cn":"fill-up-rate","ct":58},{"cc":5652,"cn":"misfeed-ballots","ct":562},{"cc":5652,"cn":"number-of-voters-who-actually-voted","ct":9077},{"cc":5652,"cn":"overvote-ballots","ct":888},{"cc":5652,"cn":"overvote-count","ct":0},{"cc":5652,"cn":"overvotes","ct":0},{"cc":5652,"cn":"processed-ballots","ct":9077},{"cc":5652,"cn":"processed-count","ct":9077},{"cc":5652,"cn":"reported-expected-precincts","ct":22},{"cc":5652,"cn":"reported-expected-voters","ct":10711},{"cc":5652,"cn":"reported-precincts","ct":22},{"cc":5652,"cn":"reported-vb","ct":22},{"cc":5652,"cn":"reported-voters","ct":10711},{"cc":5652,"cn":"returned-ballots","ct":613},{"cc":5652,"cn":"rezeros","ct":44},{"cc":5652,"cn":"tra-vb","ct":100},{"cc":5652,"cn":"turn-out","ct":84.74},{"cc":5652,"cn":"under-votes","ct":3681},{"cc":5652,"cn":"undervote-ballots","ct":8018},{"cc":5652,"cn":"undervote-count","ct":3803},{"cc":5652,"cn":"undervotes","ct":3803},{"cc":5652,"cn":"valid-ballot-rate","ct":100},{"cc":5652,"cn":"valid-votes","ct":9077},{"cc":5652,"cn":"votes-obtained-by-all-candidates","ct":5274},{"cc":5652,"cn":"writein-ballots","ct":0},{"cc":5733,"cn":"blank","ct":4205},{"cc":5733,"cn":"blank-ballots","ct":122},{"cc":5733,"cn":"contest-abstention-votes","ct":122},{"cc":5733,"cn":"expected-vb","ct":22},{"cc":5733,"cn":"expected-voters","ct":10711},{"cc":5733,"cn":"fake-ballots","ct":36},{"cc":5733,"cn":"fill-up-rate","ct":54},{"cc":5733,"cn":"misfeed-ballots","ct":562},{"cc":5733,"cn":"number-of-voters-who-actually-voted","ct":9077},{"cc":5733,"cn":"overvote-ballots","ct":888},{"cc":5733,"cn":"overvote-count","ct":0},{"cc":5733,"cn":"overvotes","ct":0},{"cc":5733,"cn":"processed-ballots","ct":9077},{"cc":5733,"cn":"processed-count","ct":9077},{"cc":5733,"cn":"reported-expected-precincts","ct":22},{"cc":5733,"cn":"reported-expected-voters","ct":10711},{"cc":5733,"cn":"reported-precincts","ct":22},{"cc":5733,"cn":"reported-vb","ct":22},{"cc":5733,"cn":"reported-voters","ct":10711},{"cc":5733,"cn":"returned-ballots","ct":613},{"cc":5733,"cn":"rezeros","ct":44},{"cc":5733,"cn":"tra-vb","ct":100},{"cc":5733,"cn":"turn-out","ct":84.74},{"cc":5733,"cn":"under-votes","ct":4083},{"cc":5733,"cn":"undervote-ballots","ct":8018},{"cc":5733,"cn":"undervote-count","ct":4205},{"cc":5733,"cn":"undervotes","ct":4205},{"cc":5733,"cn":"valid-ballot-rate","ct":100},{"cc":5733,"cn":"valid-votes","ct":9077},{"cc":5733,"cn":"votes-obtained-by-all-candidates","ct":4872},{"cc":5733,"cn":"writein-ballots","ct":0},{"cc":5939,"cn":"blank","ct":1916},{"cc":5939,"cn":"blank-ballots","ct":122},{"cc":5939,"cn":"contest-abstention-votes","ct":488},{"cc":5939,"cn":"expected-vb","ct":22},{"cc":5939,"cn":"expected-voters","ct":10711},{"cc":5939,"cn":"fake-ballots","ct":36},{"cc":5939,"cn":"fill-up-rate","ct":50},{"cc":5939,"cn":"misfeed-ballots","ct":562},{"cc":5939,"cn":"number-of-voters-who-actually-voted","ct":9077},{"cc":5939,"cn":"overvote-ballots","ct":888},{"cc":5939,"cn":"overvote-count","ct":26},{"cc":5939,"cn":"overvotes","ct":46},{"cc":5939,"cn":"processed-ballots","ct":9077},{"cc":5939,"cn":"processed-count","ct":9077},{"cc":5939,"cn":"reported-expected-precincts","ct":22},{"cc":5939,"cn":"reported-expected-voters","ct":10711},{"cc":5939,"cn":"reported-precincts","ct":22},{"cc":5939,"cn":"reported-vb","ct":22},{"cc":5939,"cn":"reported-voters","ct":10711},{"cc":5939,"cn":"returned-ballots","ct":613},{"cc":5939,"cn":"rezeros","ct":44},{"cc":5939,"cn":"tra-vb","ct":100},{"cc":5939,"cn":"turn-out","ct":84.74},{"cc":5939,"cn":"under-votes","ct":17473},{"cc":5939,"cn":"undervote-ballots","ct":8018},{"cc":5939,"cn":"undervote-count","ct":6354},{"cc":5939,"cn":"undervotes","ct":17961},{"cc":5939,"cn":"valid-ballot-rate","ct":100},{"cc":5939,"cn":"valid-votes","ct":36308},{"cc":5939,"cn":"votes-obtained-by-all-candidates","ct":18243},{"cc":5939,"cn":"writein-ballots","ct":0},{"cc":6171,"cn":"blank","ct":1391},{"cc":6171,"cn":"blank-ballots","ct":122},{"cc":6171,"cn":"contest-abstention-votes","ct":122},{"cc":6171,"cn":"expected-vb","ct":22},{"cc":6171,"cn":"expected-voters","ct":10711},{"cc":6171,"cn":"fake-ballots","ct":36},{"cc":6171,"cn":"fill-up-rate","ct":83},{"cc":6171,"cn":"misfeed-ballots","ct":562},{"cc":6171,"cn":"number-of-voters-who-actually-voted","ct":9077},{"cc":6171,"cn":"overvote-ballots","ct":888},{"cc":6171,"cn":"overvote-count","ct":139},{"cc":6171,"cn":"overvotes","ct":158},{"cc":6171,"cn":"processed-ballots","ct":9077},{"cc":6171,"cn":"processed-count","ct":9077},{"cc":6171,"cn":"reported-expected-precincts","ct":22},{"cc":6171,"cn":"reported-expected-voters","ct":10711},{"cc":6171,"cn":"reported-precincts","ct":22},{"cc":6171,"cn":"reported-vb","ct":22},{"cc":6171,"cn":"reported-voters","ct":10711},{"cc":6171,"cn":"returned-ballots","ct":613},{"cc":6171,"cn":"rezeros","ct":44},{"cc":6171,"cn":"tra-vb","ct":100},{"cc":6171,"cn":"turn-out","ct":84.74},{"cc":6171,"cn":"under-votes","ct":1269},{"cc":6171,"cn":"undervote-ballots","ct":8018},{"cc":6171,"cn":"undervote-count","ct":1391},{"cc":6171,"cn":"undervotes","ct":1391},{"cc":6171,"cn":"valid-ballot-rate","ct":100},{"cc":6171,"cn":"valid-votes","ct":9077},{"cc":6171,"cn":"votes-obtained-by-all-candidates","ct":7547},{"cc":6171,"cn":"writein-ballots","ct":0},{"cc":7591,"cn":"blank","ct":785},{"cc":7591,"cn":"blank-ballots","ct":122},{"cc":7591,"cn":"contest-abstention-votes","ct":122},{"cc":7591,"cn":"expected-vb","ct":22},{"cc":7591,"cn":"expected-voters","ct":10711},{"cc":7591,"cn":"fake-ballots","ct":36},{"cc":7591,"cn":"fill-up-rate","ct":91},{"cc":7591,"cn":"misfeed-ballots","ct":562},{"cc":7591,"cn":"number-of-voters-who-actually-voted","ct":9077},{"cc":7591,"cn":"overvote-ballots","ct":888},{"cc":7591,"cn":"overvote-count","ct":20},{"cc":7591,"cn":"overvotes","ct":20},{"cc":7591,"cn":"processed-ballots","ct":9077},{"cc":7591,"cn":"processed-count","ct":9077},{"cc":7591,"cn":"reported-expected-precincts","ct":22},{"cc":7591,"cn":"reported-expected-voters","ct":10711},{"cc":7591,"cn":"reported-precincts","ct":22},{"cc":7591,"cn":"reported-vb","ct":22},{"cc":7591,"cn":"reported-voters","ct":10711},{"cc":7591,"cn":"returned-ballots","ct":613},{"cc":7591,"cn":"rezeros","ct":44},{"cc":7591,"cn":"tra-vb","ct":100},{"cc":7591,"cn":"turn-out","ct":84.74},{"cc":7591,"cn":"under-votes","ct":663},{"cc":7591,"cn":"undervote-ballots","ct":8018},{"cc":7591,"cn":"undervote-count","ct":785},{"cc":7591,"cn":"undervotes","ct":785},{"cc":7591,"cn":"valid-ballot-rate","ct":100},{"cc":7591,"cn":"valid-votes","ct":9077},{"cc":7591,"cn":"votes-obtained-by-all-candidates","ct":8272},{"cc":7591,"cn":"writein-ballots","ct":0},{"cc":9225,"cn":"blank","ct":1814},{"cc":9225,"cn":"blank-ballots","ct":122},{"cc":9225,"cn":"contest-abstention-votes","ct":122},{"cc":9225,"cn":"expected-vb","ct":22},{"cc":9225,"cn":"expected-voters","ct":10711},{"cc":9225,"cn":"fake-ballots","ct":36},{"cc":9225,"cn":"fill-up-rate","ct":80},{"cc":9225,"cn":"misfeed-ballots","ct":562},{"cc":9225,"cn":"number-of-voters-who-actually-voted","ct":9077},{"cc":9225,"cn":"overvote-ballots","ct":888},{"cc":9225,"cn":"overvote-count","ct":14},{"cc":9225,"cn":"overvotes","ct":14},{"cc":9225,"cn":"processed-ballots","ct":9077},{"cc":9225,"cn":"processed-count","ct":9077},{"cc":9225,"cn":"reported-expected-precincts","ct":22},{"cc":9225,"cn":"reported-expected-voters","ct":10711},{"cc":9225,"cn":"reported-precincts","ct":22},{"cc":9225,"cn":"reported-vb","ct":22},{"cc":9225,"cn":"reported-voters","ct":10711},{"cc":9225,"cn":"returned-ballots","ct":613},{"cc":9225,"cn":"rezeros","ct":44},{"cc":9225,"cn":"tra-vb","ct":100},{"cc":9225,"cn":"turn-out","ct":84.74},{"cc":9225,"cn":"under-votes","ct":1692},{"cc":9225,"cn":"undervote-ballots","ct":8018},{"cc":9225,"cn":"undervote-count","ct":1814},{"cc":9225,"cn":"undervotes","ct":1814},{"cc":9225,"cn":"valid-ballot-rate","ct":100},{"cc":9225,"cn":"valid-votes","ct":9077},{"cc":9225,"cn":"votes-obtained-by-all-candidates","ct":7249},{"cc":9225,"cn":"writein-ballots","ct":0},{"cc":10876,"cn":"blank","ct":249},{"cc":10876,"cn":"blank-ballots","ct":122},{"cc":10876,"cn":"contest-abstention-votes","ct":976},{"cc":10876,"cn":"expected-vb","ct":22},{"cc":10876,"cn":"expected-voters","ct":10711},{"cc":10876,"cn":"fake-ballots","ct":36},{"cc":10876,"cn":"fill-up-rate","ct":77},{"cc":10876,"cn":"misfeed-ballots","ct":562},{"cc":10876,"cn":"number-of-voters-who-actually-voted","ct":9077},{"cc":10876,"cn":"overvote-ballots","ct":888},{"cc":10876,"cn":"overvote-count","ct":331},{"cc":10876,"cn":"overvotes","ct":717},{"cc":10876,"cn":"processed-ballots","ct":9077},{"cc":10876,"cn":"processed-count","ct":9077},{"cc":10876,"cn":"reported-expected-precincts","ct":22},{"cc":10876,"cn":"reported-expected-voters","ct":10711},{"cc":10876,"cn":"reported-precincts","ct":22},{"cc":10876,"cn":"reported-vb","ct":22},{"cc":10876,"cn":"reported-voters","ct":10711},{"cc":10876,"cn":"returned-ballots","ct":613},{"cc":10876,"cn":"rezeros","ct":44},{"cc":10876,"cn":"tra-vb","ct":100},{"cc":10876,"cn":"turn-out","ct":84.74},{"cc":10876,"cn":"under-votes","ct":13058},{"cc":10876,"cn":"undervote-ballots","ct":8018},{"cc":10876,"cn":"undervote-count","ct":3957},{"cc":10876,"cn":"undervotes","ct":14034},{"cc":10876,"cn":"valid-ballot-rate","ct":100},{"cc":10876,"cn":"valid-votes","ct":72616},{"cc":10876,"cn":"votes-obtained-by-all-candidates","ct":55934},{"cc":10876,"cn":"writein-ballots","ct":0},{"cc":11172,"cn":"blank","ct":2917},{"cc":11172,"cn":"blank-ballots","ct":122},{"cc":11172,"cn":"contest-abstention-votes","ct":122},{"cc":11172,"cn":"expected-vb","ct":22},{"cc":11172,"cn":"expected-voters","ct":10711},{"cc":11172,"cn":"fake-ballots","ct":36},{"cc":11172,"cn":"fill-up-rate","ct":65},{"cc":11172,"cn":"misfeed-ballots","ct":562},{"cc":11172,"cn":"number-of-voters-who-actually-voted","ct":9077},{"cc":11172,"cn":"overvote-ballots","ct":888},{"cc":11172,"cn":"overvote-count","ct":291},{"cc":11172,"cn":"overvotes","ct":828},{"cc":11172,"cn":"processed-ballots","ct":9077},{"cc":11172,"cn":"processed-count","ct":9077},{"cc":11172,"cn":"reported-expected-precincts","ct":22},{"cc":11172,"cn":"reported-expected-voters","ct":10711},{"cc":11172,"cn":"reported-precincts","ct":22},{"cc":11172,"cn":"reported-vb","ct":22},{"cc":11172,"cn":"reported-voters","ct":10711},{"cc":11172,"cn":"returned-ballots","ct":613},{"cc":11172,"cn":"rezeros","ct":44},{"cc":11172,"cn":"tra-vb","ct":100},{"cc":11172,"cn":"turn-out","ct":84.74},{"cc":11172,"cn":"under-votes","ct":2795},{"cc":11172,"cn":"undervote-ballots","ct":8018},{"cc":11172,"cn":"undervote-count","ct":2917},{"cc":11172,"cn":"undervotes","ct":2917},{"cc":11172,"cn":"valid-ballot-rate","ct":100},{"cc":11172,"cn":"valid-votes","ct":9077},{"cc":11172,"cn":"votes-obtained-by-all-candidates","ct":5869},{"cc":11172,"cn":"writein-ballots","ct":0}],"sts":{"expected":11,"received":11,"per":"100.00"},"obs":[]}